earlgrey/__init__.py
earlgrey/message_queue_connection.py
earlgrey/message_queue_info.py
earlgrey/message_queue_service.py
earlgrey/message_queue_stub.py
earlgrey/message_queue_task.py
earlgrey/version.py
earlgrey/patterns/__init__.py
earlgrey/patterns/rpc/__init__.py
earlgrey/patterns/rpc/client_async.py
earlgrey/patterns/rpc/client_sync.py
earlgrey/patterns/rpc/server.py
earlgrey/patterns/worker/__init__.py
earlgrey/patterns/worker/client_async.py
earlgrey/patterns/worker/client_sync.py
earlgrey/patterns/worker/server.py
test/__init__.py
test/test_basic.py
test/test_callback.py
test/test_multiprocess.py
earlgrey-0.2.2.dist-info/LICENSE
earlgrey-0.2.2.dist-info/METADATA
earlgrey-0.2.2.dist-info/WHEEL
earlgrey-0.2.2.dist-info/top_level.txt
earlgrey-0.2.2.dist-info/RECORD
