Metadata-Version: 2.1
Name: earlgrey
Version: 0.2.2
Summary: Python AMQP RPC library
Home-page: https://github.com/icon-project/earlgrey
Author: ICON foundation
License: Apache License 2.0
Platform: UNKNOWN
Classifier: Development Status :: 5 - Production/Stable
Classifier: Intended Audience :: Developers
Classifier: Intended Audience :: System Administrators
Classifier: Natural Language :: English
Classifier: License :: OSI Approved :: Apache Software License
Classifier: Programming Language :: Python
Classifier: Programming Language :: Python :: 3.6
Classifier: Programming Language :: Python :: 3.7
Requires-Dist: aio-pika (~=6.7.1)
Requires-Dist: pika (~=1.1.0)
Provides-Extra: test
Requires-Dist: pytest (~=5.4.2) ; extra == 'test'
Requires-Dist: mock (~=4.0.1) ; extra == 'test'
